csvinsight/__init__.py
csvinsight/cli.py
csvinsight/split.py
csvinsight/summarize.py
csvinsight-0.4.0.dist-info/AUTHORS.rst
csvinsight-0.4.0.dist-info/LICENSE
csvinsight-0.4.0.dist-info/METADATA
csvinsight-0.4.0.dist-info/WHEEL
csvinsight-0.4.0.dist-info/entry_points.txt
csvinsight-0.4.0.dist-info/top_level.txt
csvinsight-0.4.0.dist-info/RECORD
