Metadata-Version: 2.1
Name: csvinsight
Version: 0.4.0
Summary: Fast & simple summary for large CSV files
Home-page: https://github.com/ProfoundNetworks/csvinsight
Author: Michael Penkov
Author-email: m@penkov.dev
License: MIT license
Keywords: csvinsight
Classifier: Development Status :: 2 - Pre-Alpha
Classifier: Intended Audience :: Developers
Classifier: License :: OSI Approved :: MIT License
Classifier: Natural Language :: English
Classifier: Programming Language :: Python :: 3.8
Classifier: Programming Language :: Python :: 3.9
Classifier: Programming Language :: Python :: 3.10
Classifier: Programming Language :: Python :: 3.11
Requires-Python: >=3.8
License-File: LICENSE
License-File: AUTHORS.rst
Requires-Dist: plumbum
Requires-Dist: pyyaml
